specchio/__init__.py
specchio/const.py
specchio/handlers.py
specchio/main.py
specchio/utils.py
specchio/config/__init__.py
specchio/config/logging.py
Specchio-0.1.2.dist-info/DESCRIPTION.rst
Specchio-0.1.2.dist-info/entry_points.txt
Specchio-0.1.2.dist-info/METADATA
Specchio-0.1.2.dist-info/metadata.json
Specchio-0.1.2.dist-info/pbr.json
Specchio-0.1.2.dist-info/RECORD
Specchio-0.1.2.dist-info/top_level.txt
Specchio-0.1.2.dist-info/WHEEL
