Metadata-Version: 2.0
Name: Specchio
Version: 0.1.2
Summary: Specchio is a tool that can help you to rsync your file automatically, it uses `.gitignore` in git to discern which file is ignored.
Home-page: https://github.com/brickgao/specchio
Author: Xiongzhi Gao
Author-email: brickgao@gmail.com
License: MIT
Platform: UNKNOWN
Classifier: Environment :: Console
Classifier: Intended Audience :: Developers
Classifier: License :: OSI Approved :: MIT License
Classifier: Programming Language :: Python
Classifier: Programming Language :: Python :: 2
Classifier: Topic :: Software Development :: Testing
Classifier: Topic :: Software Development :: Libraries :: Python Modules
Requires-Dist: colorlog (>=2.6.0,<3.0.0)
Requires-Dist: watchdog (>=0.8.3,<1.0.0)
Requires-Dist: mock (>=1.0.1,<2.0.0)
Requires-Dist: testfixtures (>=4.1.2,<5.0.0)
